[
 {"url": "https://files.catbox.moe/auixly.jpg"},
 {"url": "https://files.catbox.moe/z05v0y.jpg"},
 {"url": "https://files.catbox.moe/yffg7i.jpg"},
 {"url": "https://files.catbox.moe/ebnb4r.jpg"},
 {"url": "https://files.catbox.moe/vs17x4.jpg"},
 {"url": "https://files.catbox.moe/qea7lp.jpg"},
 {"url": "https://files.catbox.moe/m1h6bo.jpg"},
 {"url": "https://files.catbox.moe/kg7404.jpg"},
 {"url": "https://files.catbox.moe/b5bv9l.jpg"},
 {"url": "https://files.catbox.moe/b5bv9l.jpg"},
 {"url": "https://files.catbox.moe/6ozmoz.jpg"},
 {"url": "https://files.catbox.moe/hhavuh.jpg"},
 {"url": "https://files.catbox.moe/lzmf1m.jpg"},
 {"url": "https://files.catbox.moe/3yw4az.jpg"},
 {"url": "https://files.catbox.moe/1woyte.jpg"},
 {"url": "https://files.catbox.moe/yawz3u.jpg"},
 {"url": "https://files.catbox.moe/f55lf4.jpg"},
 {"url": "https://files.catbox.moe/p9nist.jpg"},
 {"url": "https://files.catbox.moe/ieyo3x.jpg"},
 {"url": "https://files.catbox.moe/ieyo3x.jpg"},
 {"url": "https://files.catbox.moe/kwqwkx.jpg"},
 {"url": "https://files.catbox.moe/txv9xv.jpg"},
 {"url": "https://files.catbox.moe/hsseou.jpg"},
 {"url": "https://endpoint.web.id/server/file/rqyIfiH3EEROCh2D.jpg"},
 {"url": "https://endpoint.web.id/server/file/xM720pUA7Khb8LFx.jpg"},
 {"url": "https://endpoint.web.id/server/file/Bo21zcYpO93m9taq.png"},
  {"url": "https://files.catbox.moe/auixly.jpg"},
 {"url": "https://files.catbox.moe/q1pybs.jpg"},
 {"url": "https://files.catbox.moe/d13pad.jpg"},
 {"url": "https://files.catbox.moe/vd31kn.jpg"},
 {"url": "https://files.catbox.moe/femjvi.jpg"},
 {"url": "https://files.catbox.moe/82s114.jpg"},
 {"url": "https://files.catbox.moe/gfdz4j.jpg"},
 {"url": "https://files.catbox.moe/6yfkz8.jpg"},
 {"url": "https://files.catbox.moe/4kzbsn.jpg"},
 {"url": "https://files.catbox.moe/3xtyls.jpg"},
 {"url": "https://files.catbox.moe/w21jdk.jpg"}
]
